slowtestreporter/__init__.py
slowtestreporter/cli.py
slowtestreporter/slowtestreporter.py
slowtestreporter-0.0.7.dist-info/LICENSE
slowtestreporter-0.0.7.dist-info/METADATA
slowtestreporter-0.0.7.dist-info/WHEEL
slowtestreporter-0.0.7.dist-info/entry_points.txt
slowtestreporter-0.0.7.dist-info/top_level.txt
slowtestreporter-0.0.7.dist-info/RECORD
