Metadata-Version: 2.1
Name: slowtestreporter
Version: 0.0.7
Summary: A small python package for reporting slow tests.
Project-URL: Homepage, https://github.com/jerrylu8888/slowtestreporter
Project-URL: Bug Tracker, https://github.com/jerrylu8888/slowtestreporter/issues
Classifier: Programming Language :: Python :: 3
Requires-Python: >=3.7
License-File: LICENSE
Requires-Dist: attrs
Requires-Dist: exceptiongroup
Requires-Dist: future
Requires-Dist: junitparser
Requires-Dist: pluggy
Requires-Dist: tabulate
Requires-Dist: tomli
